setup.py
selfcmp/__init__.py
selfcmp/datamk.py
selfcmp/filewk.py
selfcmp/help.py
selfcmp/pro.py
selfcmp/spw.py
selfcmp/work.py
selfcmp.egg-info/PKG-INFO
selfcmp.egg-info/SOURCES.txt
selfcmp.egg-info/dependency_links.txt
selfcmp.egg-info/top_level.txt