Metadata-Version: 1.0
Name: selfcmp
Version: 0.0.3.0
Summary: find the error in your program! For OIer and ACMer
Home-page: https://gitlab.com/VictoryCzt/selfcmp
Author: VictoryCzt
Author-email: 1251939098@qq.com
License: UNKNOWN
Platform: UNKNOWN
